scd30/scd30.py
scd30-0.0.3.dist-info/LICENSE
scd30-0.0.3.dist-info/METADATA
scd30-0.0.3.dist-info/WHEEL
scd30-0.0.3.dist-info/top_level.txt
scd30-0.0.3.dist-info/RECORD
