Metadata-Version: 2.1
Name: scd30
Version: 0.0.3
Summary: Python 3 library for the Sensirion SCD30 sensor
Home-page: https://github.com/laurenzgamper/scd30
Author: Laurenz Gamper
Author-email: laurenzgamper@gmail.com
License: UNKNOWN
Platform: UNKNOWN
Classifier: Programming Language :: Python :: 3
Classifier: Operating System :: OS Independent
Requires-Python: >=3.6
Requires-Dist: crcmod
Requires-Dist: pigpio
